ParseLexer/__init__.py
ParseLexer/strings_with_arrows.py
ParserLexing-0.0.1.dist-info/METADATA
ParserLexing-0.0.1.dist-info/WHEEL
ParserLexing-0.0.1.dist-info/top_level.txt
ParserLexing-0.0.1.dist-info/RECORD
