Metadata-Version: 2.1
Name: ParserLexing
Version: 0.0.1
Summary: A library for lexing and parsing
Author: Amir Sabri
Author-email: amirsbry1942@gmail.com
